dream_helpers/__init__.py
dream_helpers/datahub_helper.py
dream_helpers/kubeflow_helper.py
dream_helpers/minio_helper.py
dream_helpers-0.0.333.dist-info/METADATA
dream_helpers-0.0.333.dist-info/WHEEL
dream_helpers-0.0.333.dist-info/RECORD
